CHANGELOG.md
CONTRIBUTING.md
DESCRIPTION.md
LICENSE
MANIFEST.in
README.md
setup.py
tests.py
coloratura/__init__.py
coloratura/colors.py
coloratura/main.py
coloratura.egg-info/PKG-INFO
coloratura.egg-info/SOURCES.txt
coloratura.egg-info/dependency_links.txt
coloratura.egg-info/top_level.txt
venv/Lib/site-packages/_black_version.py
venv/Lib/site-packages/_virtualenv.py
venv/Lib/site-packages/delegator.py
venv/Lib/site-packages/end.py
venv/Lib/site-packages/mypy_extensions.py
venv/Lib/site-packages/pink.py
venv/Lib/site-packages/_distutils_hack/__init__.py
venv/Lib/site-packages/_distutils_hack/override.py
venv/Lib/site-packages/black/__init__.py
venv/Lib/site-packages/black/__main__.py
venv/Lib/site-packages/black/brackets.py
venv/Lib/site-packages/black/cache.py
venv/Lib/site-packages/black/comments.py
venv/Lib/site-packages/black/concurrency.py
venv/Lib/site-packages/black/const.py
venv/Lib/site-packages/black/debug.py
venv/Lib/site-packages/black/files.py
venv/Lib/site-packages/black/handle_ipynb_magics.py
venv/Lib/site-packages/black/linegen.py
venv/Lib/site-packages/black/lines.py
venv/Lib/site-packages/black/mode.py
venv/Lib/site-packages/black/nodes.py
venv/Lib/site-packages/black/numerics.py
venv/Lib/site-packages/black/output.py
venv/Lib/site-packages/black/parsing.py
venv/Lib/site-packages/black/report.py
venv/Lib/site-packages/black/rusty.py
venv/Lib/site-packages/black/strings.py
venv/Lib/site-packages/black/trans.py
venv/Lib/site-packages/black-22.1.0.dist-info/AUTHORS.md
venv/Lib/site-packages/black_primer/__init__.py
venv/Lib/site-packages/black_primer/cli.py
venv/Lib/site-packages/black_primer/lib.py
venv/Lib/site-packages/blackd/__init__.py
venv/Lib/site-packages/blackd/__main__.py
venv/Lib/site-packages/blackd/middlewares.py
venv/Lib/site-packages/blib2to3/__init__.py
venv/Lib/site-packages/blib2to3/pygram.py
venv/Lib/site-packages/blib2to3/pytree.py
venv/Lib/site-packages/blib2to3/pgen2/__init__.py
venv/Lib/site-packages/blib2to3/pgen2/conv.py
venv/Lib/site-packages/blib2to3/pgen2/driver.py
venv/Lib/site-packages/blib2to3/pgen2/grammar.py
venv/Lib/site-packages/blib2to3/pgen2/literals.py
venv/Lib/site-packages/blib2to3/pgen2/parse.py
venv/Lib/site-packages/idna-3.3.dist-info/LICENSE.md
