Metadata-Version: 2.1
Name: coloratura
Version: 1.0
Summary: 🦜Awesome cprint() function to colored terminal text. Supported full RGB!
Home-page: https://github.com/DawidKos/Coloratura
Author: pyblog.pl
Author-email: rewolucjazywieniowa@gmail.com
License: MIT
Keywords: color,colored,colour,terminal,text,ansi,colorama,hue
Platform: UNKNOWN
Classifier: Development Status :: 5 - Production/Stable
Classifier: Intended Audience :: Developers
Classifier: Programming Language :: Python :: 3
Classifier: License :: OSI Approved :: MIT License
Classifier: Programming Language :: Python
Classifier: Environment :: Plugins
License-File: LICENSE
